libvoikko.py
libvoikko-4.3.dist-info/METADATA
libvoikko-4.3.dist-info/WHEEL
libvoikko-4.3.dist-info/top_level.txt
libvoikko-4.3.dist-info/RECORD
